artifact_core/__init__.py
artifact_core/_base/__init__.py
artifact_core/_base/core/__init__.py
artifact_core/_base/core/artifact.py
artifact_core/_base/core/hyperparams.py
artifact_core/_base/core/resource_spec.py
artifact_core/_base/core/resources.py
artifact_core/_base/orchestration/__init__.py
artifact_core/_base/orchestration/engine.py
artifact_core/_base/orchestration/key_formatter.py
artifact_core/_base/orchestration/registry.py
artifact_core/_base/orchestration/repository.py
artifact_core/_base/orchestration/repository_reader.py
artifact_core/_base/orchestration/repository_writer.py
artifact_core/_base/primitives/artifact_type.py
artifact_core/_base/typing/artifact_result.py
artifact_core/_bootstrap/__init__.py
artifact_core/_bootstrap/config/__init__.py
artifact_core/_bootstrap/config/config_reader.py
artifact_core/_bootstrap/config/override_locator.py
artifact_core/_bootstrap/config/toolkit_config.py
artifact_core/_bootstrap/primitives/__init__.py
artifact_core/_bootstrap/primitives/domain_toolkit.py
artifact_core/_bootstrap/toolkit_initializer.py
artifact_core/_domains/__init__.py
artifact_core/_domains/classification/__init__.py
artifact_core/_domains/classification/artifact.py
artifact_core/_domains/classification/engine.py
artifact_core/_domains/classification/registry.py
artifact_core/_domains/classification/resources.py
artifact_core/_domains/dataset_comparison/__init__.py
artifact_core/_domains/dataset_comparison/artifact.py
artifact_core/_domains/dataset_comparison/engine.py
artifact_core/_domains/dataset_comparison/registry.py
artifact_core/_domains/dataset_comparison/resources.py
artifact_core/_interfaces/__init__.py
artifact_core/_interfaces/serializable.py
artifact_core/_libs/__init__.py
artifact_core/_libs/artifacts/__init__.py
artifact_core/_libs/artifacts/binary_classification/__init__.py
artifact_core/_libs/artifacts/binary_classification/confusion/__init__.py
artifact_core/_libs/artifacts/binary_classification/confusion/calculator.py
artifact_core-0.2.0.dist-info/METADATA
artifact_core-0.2.0.dist-info/WHEEL
artifact_core-0.2.0.dist-info/RECORD
