Metadata-Version: 2.4
Name: artifact-core
Version: 0.2.0
Summary: Artifact-ML foundation: a declarative interface for the computation of validation artifacts in ML experiments.
License: MIT
Author: Vasileios Ektor Papoulias
Author-email: hector.papoulias@gmail.com
Requires-Python: >=3.11,<3.14
Classifier: License :: OSI Approved :: MIT License
Classifier: Programming Language :: Python :: 3
Classifier: Programming Language :: Python :: 3.11
Classifier: Programming Language :: Python :: 3.12
Classifier: Programming Language :: Python :: 3.13
Requires-Dist: dython (>=0.7.9,<0.8.0)
Requires-Dist: matplotlib (>=3.10.1,<4.0.0)
Requires-Dist: numpy (>=2.2.4,<3.0.0)
Requires-Dist: pandas (>=2.2.3,<3.0.0)
Requires-Dist: scikit-learn (>=1.6.1,<2.0.0)
Requires-Dist: seaborn (>=0.13.2,<0.14.0)
Project-URL: Bug Tracker, https://github.com/vasileios-ektor-papoulias/artifact-ml/issues
Project-URL: Documentation, https://artifact-ml.readthedocs.io/en/latest/artifact-core
Project-URL: Homepage, https://github.com/vasileios-ektor-papoulias/artifact-ml
Project-URL: Repository, https://github.com/vasileios-ektor-papoulias/artifact-ml
